odoo/addons/stock_move_source_relocate_dynamic_routing/README.rst
odoo/addons/stock_move_source_relocate_dynamic_routing/__init__.py
odoo/addons/stock_move_source_relocate_dynamic_routing/__manifest__.py
odoo/addons/stock_move_source_relocate_dynamic_routing/i18n/es_AR.po
odoo/addons/stock_move_source_relocate_dynamic_routing/i18n/stock_move_source_relocate_dynamic_routing.pot
odoo/addons/stock_move_source_relocate_dynamic_routing/models/__init__.py
odoo/addons/stock_move_source_relocate_dynamic_routing/models/stock_move.py
odoo/addons/stock_move_source_relocate_dynamic_routing/models/stock_routing.py
odoo/addons/stock_move_source_relocate_dynamic_routing/models/stock_source_relocate.py
odoo/addons/stock_move_source_relocate_dynamic_routing/readme/CONTRIBUTORS.rst
odoo/addons/stock_move_source_relocate_dynamic_routing/readme/DESCRIPTION.rst
odoo/addons/stock_move_source_relocate_dynamic_routing/static/description/icon.png
odoo/addons/stock_move_source_relocate_dynamic_routing/static/description/index.html
odoo/addons/stock_move_source_relocate_dynamic_routing/tests/__init__.py
odoo/addons/stock_move_source_relocate_dynamic_routing/tests/test_dynamic_destination.py
odoo/addons/stock_move_source_relocate_dynamic_routing/tests/test_dynamic_relocate.py
odoo/addons/stock_move_source_relocate_dynamic_routing/views/stock_routing_views.xml
odoo/addons/stock_move_source_relocate_dynamic_routing/views/stock_source_relocate_views.xml
odoo13_addon_stock_move_source_relocate_dynamic_routing-13.0.1.1.2.dist-info/METADATA
odoo13_addon_stock_move_source_relocate_dynamic_routing-13.0.1.1.2.dist-info/WHEEL
odoo13_addon_stock_move_source_relocate_dynamic_routing-13.0.1.1.2.dist-info/top_level.txt
odoo13_addon_stock_move_source_relocate_dynamic_routing-13.0.1.1.2.dist-info/RECORD
